mullvadshal/__init__.py
mullvadshal/__main__.py
mullvadshal/main.py
mullvadshal-1.0.1.dist-info/LICENSE
mullvadshal-1.0.1.dist-info/METADATA
mullvadshal-1.0.1.dist-info/WHEEL
mullvadshal-1.0.1.dist-info/entry_points.txt
mullvadshal-1.0.1.dist-info/top_level.txt
mullvadshal-1.0.1.dist-info/RECORD
