Metadata-Version: 2.2
Name: mullvadshal
Version: 1.0.1
Summary: Mullvadshål is utomated server-hopping for Mullvad VPN for WireGuard and Linux
Home-page: https://github.com/Addvilz/mullvadshal
Download-URL: https://github.com/Addvilz/mullvadshal
Author: Addvilz
Author-email: mrtreinis@gmail.com
License: Apache 2.0
Platform: UNIX
Classifier: Development Status :: 4 - Beta
Classifier: Environment :: Console
Classifier: License :: OSI Approved :: Apache Software License
Classifier: Operating System :: POSIX :: Linux
Classifier: Operating System :: POSIX
Classifier: Operating System :: Unix
Classifier: Programming Language :: Python :: 3 :: Only
License-File: LICENSE
Requires-Dist: requests>=2.31.0
Requires-Dist: cryptography>=43.0.3
Requires-Dist: argparse
Dynamic: author
Dynamic: author-email
Dynamic: classifier
Dynamic: description
Dynamic: description-content-type
Dynamic: download-url
Dynamic: home-page
Dynamic: license
Dynamic: platform
Dynamic: requires-dist
Dynamic: summary
